pyrit/__init__.py
pyrit/show_versions.py
pyrit/analytics/__init__.py
pyrit/analytics/conversation_analytics.py
pyrit/auth/__init__.py
pyrit/auth/auth_config.py
pyrit/auth/authenticator.py
pyrit/auth/azure_auth.py
pyrit/auth/azure_storage_auth.py
pyrit/chat_message_normalizer/__init__.py
pyrit/chat_message_normalizer/chat_message_nop.py
pyrit/chat_message_normalizer/chat_message_normalizer.py
pyrit/chat_message_normalizer/chat_message_normalizer_chatml.py
pyrit/chat_message_normalizer/chat_message_normalizer_tokenizer.py
pyrit/chat_message_normalizer/generic_system_squash.py
pyrit/common/__init__.py
pyrit/common/cache_helper.py
pyrit/common/chat_message_builder.py
pyrit/common/csv_helper.py
pyrit/common/default_values.py
pyrit/common/display_response.py
pyrit/common/json_helper.py
pyrit/common/logger.py
pyrit/common/net_utility.py
pyrit/common/notebook_utils.py
pyrit/common/path.py
pyrit/common/print.py
pyrit/common/prompt_template_generator.py
pyrit/common/singleton.py
pyrit/common/text_helper.py
pyrit/common/yaml_loadable.py
pyrit/datasets/__init__.py
pyrit/datasets/fetch_example_datasets.py
pyrit/datasets/orchestrators/benchmark/question_answer.yaml
pyrit/datasets/orchestrators/crescendo/crescendo_variant_1.yaml
pyrit/datasets/orchestrators/crescendo/crescendo_variant_2.yaml
pyrit/datasets/orchestrators/crescendo/crescendo_variant_3.yaml
pyrit/datasets/orchestrators/crescendo/crescendo_variant_4.yaml
pyrit/datasets/orchestrators/crescendo/crescendo_variant_5.yaml
pyrit/datasets/orchestrators/pair/attacker_system_prompt.yaml
pyrit/datasets/orchestrators/red_teaming/crucible.yaml
pyrit/datasets/orchestrators/red_teaming/image_generation.yaml
pyrit/datasets/orchestrators/red_teaming/naive_crescendo.yaml
pyrit/datasets/orchestrators/red_teaming/text_generation.yaml
pyrit/datasets/orchestrators/tree_of_attacks/initial_prompt.yaml
pyrit/datasets/orchestrators/tree_of_attacks/red_teaming_prompt_template.yaml
pyrit_library-0.1.7.dist-info/METADATA
pyrit_library-0.1.7.dist-info/WHEEL
pyrit_library-0.1.7.dist-info/top_level.txt
pyrit_library-0.1.7.dist-info/RECORD
