Metadata-Version: 2.1
Name: pyrit-library
Version: 0.1.7
Requires-Dist: aioconsole
Requires-Dist: annotated-types
Requires-Dist: anyio
Requires-Dist: appdirs
Requires-Dist: argon2-cffi
Requires-Dist: argon2-cffi-bindings
Requires-Dist: arrow
Requires-Dist: art
Requires-Dist: asttokens
Requires-Dist: async-lru
Requires-Dist: attrs
Requires-Dist: azure-ai-contentsafety
Requires-Dist: azure-ai-ml
Requires-Dist: azure-cognitiveservices-speech
Requires-Dist: azure-common
Requires-Dist: azure-core
Requires-Dist: azure-identity
Requires-Dist: azure-mgmt-core
Requires-Dist: azure-storage-blob
Requires-Dist: azure-storage-file-datalake
Requires-Dist: azure-storage-file-share
Requires-Dist: babel
Requires-Dist: beautifulsoup4
Requires-Dist: bleach
Requires-Dist: cachetools
Requires-Dist: certifi
Requires-Dist: cffi
Requires-Dist: charset-normalizer
Requires-Dist: colorama
Requires-Dist: coloredlogs
Requires-Dist: comm
Requires-Dist: confusables
Requires-Dist: cryptography
Requires-Dist: debugpy
Requires-Dist: decorator
Requires-Dist: defusedxml
Requires-Dist: distro
Requires-Dist: duckdb
Requires-Dist: duckdb-engine
Requires-Dist: executing
Requires-Dist: fastjsonschema
Requires-Dist: filelock
Requires-Dist: flatbuffers
Requires-Dist: fqdn
Requires-Dist: fsspec
Requires-Dist: google-api-core
Requires-Dist: google-auth
Requires-Dist: googleapis-common-protos
Requires-Dist: greenlet
Requires-Dist: h11
Requires-Dist: httpcore
Requires-Dist: httpx
Requires-Dist: huggingface-hub
Requires-Dist: humanfriendly
Requires-Dist: idna
Requires-Dist: ipykernel
Requires-Dist: ipython
Requires-Dist: ipywidgets
Requires-Dist: isodate
Requires-Dist: isoduration
Requires-Dist: jedi
Requires-Dist: Jinja2
Requires-Dist: jiter
Requires-Dist: joblib
Requires-Dist: json5
Requires-Dist: jsonpickle
Requires-Dist: jsonpointer
Requires-Dist: jsonschema
Requires-Dist: jsonschema-specifications
Requires-Dist: jupyter
Requires-Dist: jupyter-console
Requires-Dist: jupyter-events
Requires-Dist: jupyter-lsp
Requires-Dist: jupyter-client
Requires-Dist: jupyter-core
Requires-Dist: jupyter-server
Requires-Dist: jupyter-server-terminals
Requires-Dist: jupyterlab
Requires-Dist: jupyterlab-pygments
Requires-Dist: jupyterlab-server
Requires-Dist: jupyterlab-widgets
Requires-Dist: logzero
Requires-Dist: MarkupSafe
Requires-Dist: marshmallow
Requires-Dist: matplotlib-inline
Requires-Dist: mistune
Requires-Dist: mpmath
Requires-Dist: msal
Requires-Dist: msal-extensions
Requires-Dist: msrest
Requires-Dist: mypy
Requires-Dist: mypy-extensions
Requires-Dist: nbclient
Requires-Dist: nbconvert
Requires-Dist: nbformat
Requires-Dist: nest-asyncio
Requires-Dist: notebook
Requires-Dist: notebook-shim
Requires-Dist: numpy
Requires-Dist: oauthlib
Requires-Dist: onnx
Requires-Dist: onnxruntime
Requires-Dist: openai
Requires-Dist: opencensus
Requires-Dist: opencensus-context
Requires-Dist: opencensus-ext-azure
Requires-Dist: overrides
Requires-Dist: packaging
Requires-Dist: pandocfilters
Requires-Dist: parso
Requires-Dist: pillow
Requires-Dist: platformdirs
Requires-Dist: portalocker
Requires-Dist: prometheus-client
Requires-Dist: prompt-toolkit
Requires-Dist: proto-plus
Requires-Dist: protobuf
Requires-Dist: psutil
Requires-Dist: pure-eval
Requires-Dist: pyasn1
Requires-Dist: pyasn1-modules
Requires-Dist: pycountry
Requires-Dist: pycparser
Requires-Dist: pydantic
Requires-Dist: pydantic-core
Requires-Dist: pydash
Requires-Dist: Pygments
Requires-Dist: PyJWT
Requires-Dist: pyodbc
Requires-Dist: pyreadline3
Requires-Dist: python-dateutil
Requires-Dist: python-dotenv
Requires-Dist: python-json-logger
Requires-Dist: PyYAML
Requires-Dist: pyzmq
Requires-Dist: referencing
Requires-Dist: regex
Requires-Dist: requests
Requires-Dist: requests-oauthlib
Requires-Dist: rfc3339-validator
Requires-Dist: rfc3986-validator
Requires-Dist: rpds-py
Requires-Dist: rsa
Requires-Dist: safetensors
Requires-Dist: scikit-learn
Requires-Dist: scipy
Requires-Dist: Send2Trash
Requires-Dist: six
Requires-Dist: sniffio
Requires-Dist: soupsieve
Requires-Dist: SQLAlchemy
Requires-Dist: sqlalchemy-stubs
Requires-Dist: stack-data
Requires-Dist: strictyaml
Requires-Dist: sympy
Requires-Dist: tenacity
Requires-Dist: termcolor
Requires-Dist: terminado
Requires-Dist: threadpoolctl
Requires-Dist: tinycss2
Requires-Dist: tokenizers
Requires-Dist: tornado
Requires-Dist: tqdm
Requires-Dist: traitlets
Requires-Dist: transformers
Requires-Dist: treelib
Requires-Dist: types-python-dateutil
Requires-Dist: types-requests
Requires-Dist: typing-extensions
Requires-Dist: uri-template
Requires-Dist: urllib3
Requires-Dist: wcwidth
Requires-Dist: webcolors
Requires-Dist: webencodings
Requires-Dist: websocket-client
Requires-Dist: widgetsnbextension
